bms_database_lib/__init__.py
bms_database_lib/__version__.py
bms_database_lib/base.py
bms_database_lib/base_adapter.py
bms_database_lib/connect.py
bms_database_lib/mixins.py
bms_database_lib/settings.py
bms_database_lib-0.1.2.dist-info/METADATA
bms_database_lib-0.1.2.dist-info/WHEEL
bms_database_lib-0.1.2.dist-info/RECORD
